fstringtest.py
tstpkg-0.0.1.dist-info/METADATA
tstpkg-0.0.1.dist-info/WHEEL
tstpkg-0.0.1.dist-info/top_level.txt
tstpkg-0.0.1.dist-info/RECORD
